lefaso_net_scraper/__init__.py
lefaso_net_scraper/lefaso/__init__.py
lefaso_net_scraper/lefaso/scraper.py
lefaso_net_scraper/settings.py
lefaso_net_scraper-0.4.0.dist-info/LICENSE
lefaso_net_scraper-0.4.0.dist-info/METADATA
lefaso_net_scraper-0.4.0.dist-info/WHEEL
lefaso_net_scraper-0.4.0.dist-info/RECORD
