Metadata-Version: 2.1
Name: lefaso-net-scraper
Version: 0.4.0
Summary: The ultimate library for data scientist to scrape data from https://www.lefaso.net
Home-page: https://github.com/abdoulfataoh/lefaso-net-scraper
Author: abdoulfataoh
Author-email: abdoulfataoh@gmail.com
Requires-Python: >=3.10,<4.0
Classifier: Programming Language :: Python :: 3
Classifier: Programming Language :: Python :: 3.10
Classifier: Programming Language :: Python :: 3.11
Classifier: Programming Language :: Python :: 3.12
Classifier: Programming Language :: Python :: 3.13
Provides-Extra: notebook
Requires-Dist: aiohttp (>=3.8.5,<4.0.0)
Requires-Dist: beautifulsoup4 (>=4.12.2,<5.0.0)
Requires-Dist: environs (>=9.5.0,<10.0.0)
Requires-Dist: nest-asyncio[notebook] (>=1.6.0,<2.0.0) ; extra == "notebook"
Requires-Dist: requests (>=2.31.0,<3.0.0)
Requires-Dist: unidecode (>=1.3.6,<2.0.0)
Project-URL: Documentation, https://github.com/abdoulfataoh/lefaso-net-scraper/wiki
Project-URL: Repository, https://github.com/abdoulfataoh/lefaso-net-scraper
